simple_installer/__init__.py
simple_installer/common_widgets.py
simple_installer/installFn.py
simple_installer/logger.py
simple_installer/main_dialog.py
simple_installer/pages.py
simple_installer-2.0.4.dist-info/LICENSE
simple_installer-2.0.4.dist-info/METADATA
simple_installer-2.0.4.dist-info/WHEEL
simple_installer-2.0.4.dist-info/top_level.txt
simple_installer-2.0.4.dist-info/RECORD
