Metadata-Version: 2.1
Name: simple-installer
Version: 2.0.4
Summary: Extandable installer for Github release zip files.
Home-page: UNKNOWN
Author: Dmitrii Shevchenko
Author-email: <dmitrii.shevchenko96@gmail.com>
License: UNKNOWN
Keywords: python,installer,github
Platform: UNKNOWN
Classifier: Intended Audience :: Developers
Classifier: Programming Language :: Python :: 3
Classifier: Operating System :: Unix
Classifier: Operating System :: MacOS :: MacOS X
Classifier: Operating System :: Microsoft :: Windows
Requires-Dist: PySide2
Requires-Dist: requests
Requires-Dist: PyGithub
Requires-Dist: elevate
